robotframework_reportportal/__init__.py
robotframework_reportportal/helpers.py
robotframework_reportportal/listener.py
robotframework_reportportal/logger.py
robotframework_reportportal/model.py
robotframework_reportportal/post_report.py
robotframework_reportportal/result_visitor.py
robotframework_reportportal/service.py
robotframework_reportportal/static.py
robotframework_reportportal/time_visitor.py
robotframework_reportportal/variables.py
robotframework_reportportal-5.6.5.dist-info/licenses/LICENSE.txt
robotframework_reportportal-5.6.5.dist-info/METADATA
robotframework_reportportal-5.6.5.dist-info/WHEEL
robotframework_reportportal-5.6.5.dist-info/entry_points.txt
robotframework_reportportal-5.6.5.dist-info/top_level.txt
robotframework_reportportal-5.6.5.dist-info/RECORD
