Metadata-Version: 2.4
Name: robotframework-reportportal
Version: 5.6.5
Summary: Agent for reporting RobotFramework test results to ReportPortal
Home-page: https://github.com/reportportal/agent-Python-RobotFramework
Download-URL: https://github.com/reportportal/agent-Python-RobotFramework/tarball/5.6.5
Author: ReportPortal Team
Author-email: support@reportportal.io
Keywords: testing,reporting,robot framework,reportportal,agent
Classifier: Framework :: Robot Framework
Classifier: Programming Language :: Python :: 3.8
Classifier: Programming Language :: Python :: 3.9
Classifier: Programming Language :: Python :: 3.10
Classifier: Programming Language :: Python :: 3.11
Classifier: Programming Language :: Python :: 3.12
Classifier: Programming Language :: Python :: 3.13
License-File: LICENSE.txt
Requires-Dist: python-dateutil~=2.9.0.post0
Requires-Dist: reportportal-client~=5.6.7
Requires-Dist: robotframework
Dynamic: author
Dynamic: author-email
Dynamic: classifier
Dynamic: description
Dynamic: description-content-type
Dynamic: download-url
Dynamic: home-page
Dynamic: keywords
Dynamic: license-file
Dynamic: requires-dist
Dynamic: summary
